pyomu/__init__.py
pyomu/pyomu.py
pyomu/access/__init__.py
pyomu/access/access.py
pyomu/nse/__init__.py
pyomu/nse/nse.py
pyomu/utils/__init__.py
pyomu/utils/utils.py
pyomu/utils/h3/__init__.py
pyomu/utils/h3/h3.py
pyomu/vizuals/__init__.py
pyomu/vizuals/vizuals.py
pyomu-0.2.3.dist-info/LICENSE
pyomu-0.2.3.dist-info/METADATA
pyomu-0.2.3.dist-info/WHEEL
pyomu-0.2.3.dist-info/top_level.txt
pyomu-0.2.3.dist-info/RECORD
