Metadata-Version: 2.1
Name: pyomu
Version: 0.2.3
Summary: Performs accessibility analysis
Home-page: https://github.com/pyomu
Author: Sebastián Anapolsky
Author-email: sanapolsky@gmail.com
Project-URL: Bug Tracker, https://github.com/pyomu
Classifier: Programming Language :: Python :: 3.10
Classifier: License :: OSI Approved :: MIT License
Classifier: Operating System :: OS Independent
Requires-Python: >=3.10
License-File: LICENSE
Requires-Dist: contextily ==1.4.0
Requires-Dist: folium ==0.14.0
Requires-Dist: geopandas ==0.14.0
Requires-Dist: h3 ==3.7.6
Requires-Dist: ipython ==8.16.1
Requires-Dist: jupyterlab ==4.0.6
Requires-Dist: libpysal ==4.8.0
Requires-Dist: mapclassify ==2.6.1
Requires-Dist: matplotlib-scalebar ==0.8.1
Requires-Dist: mycolorpy ==1.5.1
Requires-Dist: notebook ==7.0.4
Requires-Dist: numba ==0.58.0
Requires-Dist: numpy ==1.25.2
Requires-Dist: openpyxl ==3.1.2
Requires-Dist: pandas ==2.1.1
Requires-Dist: patsy ==0.5.3
Requires-Dist: Pillow ==9.5.0
Requires-Dist: plotly ==5.17.0
Requires-Dist: python-pptx ==0.6.22
Requires-Dist: PyYAML ==6.0.1
Requires-Dist: seaborn ==0.13.0
Requires-Dist: shapely ==2.0.1
Requires-Dist: tzwhere ==3.0.3
Requires-Dist: osmnet ==0.1.7
Requires-Dist: osmnx ==1.8.0
Requires-Dist: googlemaps ==2.5.1
Requires-Dist: pandana ==0.7
Requires-Dist: tqdm ==4.65.0
